honeybee_display/__init__.py
honeybee_display/__main__.py
honeybee_display/_extend_honeybee.py
honeybee_display/_util.py
honeybee_display/aperture.py
honeybee_display/attr.py
honeybee_display/colorobj.py
honeybee_display/door.py
honeybee_display/face.py
honeybee_display/model.py
honeybee_display/room.py
honeybee_display/shade.py
honeybee_display/shademesh.py
honeybee_display/cli/__init__.py
honeybee_display/energy/__init__.py
honeybee_display/energy/colorobj.py
honeybee_display/radiance/__init__.py
honeybee_display-0.5.7.dist-info/licenses/LICENSE
honeybee_display-0.5.7.dist-info/METADATA
honeybee_display-0.5.7.dist-info/WHEEL
honeybee_display-0.5.7.dist-info/entry_points.txt
honeybee_display-0.5.7.dist-info/top_level.txt
honeybee_display-0.5.7.dist-info/RECORD
