Metadata-Version: 2.4
Name: honeybee-display
Version: 0.5.7
Summary: Adds methods to translate honeybee objects to VisualizationSets.
Home-page: https://github.com/ladybug-tools/honeybee-display
Author: Ladybug Tools
Author-email: info@ladybug.tools
License: AGPL-3.0
Classifier: Programming Language :: Python :: 2.7
Classifier: Programming Language :: Python :: 3.7
Classifier: Programming Language :: Python :: 3.8
Classifier: Programming Language :: Python :: 3.9
Classifier: Programming Language :: Python :: 3.10
Classifier: Programming Language :: Python :: 3.11
Classifier: Programming Language :: Python :: 3.12
Classifier: Programming Language :: Python :: Implementation :: CPython
Classifier: Programming Language :: Python :: Implementation :: IronPython
Classifier: Operating System :: OS Independent
License-File: LICENSE
Requires-Dist: ladybug-display>=0.11.3
Requires-Dist: honeybee-core>=1.58.63
Provides-Extra: full
Requires-Dist: honeybee-energy>=1.95.35; extra == "full"
Requires-Dist: honeybee-radiance>=1.66.147; extra == "full"
Requires-Dist: ladybug-vtk>=0.15.2; extra == "full"
Dynamic: author
Dynamic: author-email
Dynamic: classifier
Dynamic: description
Dynamic: description-content-type
Dynamic: home-page
Dynamic: license
Dynamic: license-file
Dynamic: provides-extra
Dynamic: requires-dist
Dynamic: summary
